django_politico_kitchensink_admin-2.2.0.dist-info/METADATA
django_politico_kitchensink_admin-2.2.0.dist-info/RECORD
django_politico_kitchensink_admin-2.2.0.dist-info/WHEEL
django_politico_kitchensink_admin-2.2.0.dist-info/top_level.txt
kitchensink/__init__.py
kitchensink/admin.py
kitchensink/apps.py
kitchensink/celery.py
kitchensink/conf.py
kitchensink/signals.py
kitchensink/urls.py
kitchensink/api/__init__.py
kitchensink/api/urls.py
kitchensink/api/v1/__init__.py
kitchensink/api/v1/urls.py
kitchensink/api/v1/serializers/__init__.py
kitchensink/api/v1/serializers/archie_doc.py
kitchensink/api/v1/serializers/form_content.py
kitchensink/api/v1/serializers/form_type.py
kitchensink/api/v1/serializers/project.py
kitchensink/api/v1/serializers/sheet.py
kitchensink/api/v1/serializers/user.py
kitchensink/api/v1/viewsets/__init__.py
kitchensink/api/v1/viewsets/archie_doc.py
kitchensink/api/v1/viewsets/base.py
kitchensink/api/v1/viewsets/form_content.py
kitchensink/api/v1/viewsets/form_type.py
kitchensink/api/v1/viewsets/project.py
kitchensink/api/v1/viewsets/sheet.py
kitchensink/api/v1/viewsets/user.py
kitchensink/migrations/0001_initial.py
kitchensink/migrations/0002_auto_20181028_0420.py
kitchensink/migrations/0003_archiedoc.py
kitchensink/migrations/0004_auto_20181218_0319.py
kitchensink/migrations/0005_auto_20190825_2121.py
kitchensink/migrations/0006_auto_20191002_1940.py
kitchensink/migrations/0007_auto_20191002_1941.py
kitchensink/migrations/0008_auto_20191002_1946.py
kitchensink/migrations/0009_auto_20191002_1947.py
kitchensink/migrations/0010_auto_20191002_1952.py
kitchensink/migrations/0011_auto_20191002_1954.py
kitchensink/migrations/0012_auto_20201221_2046.py
kitchensink/migrations/0013_form.py
kitchensink/migrations/0014_formcontent.py
kitchensink/migrations/0015_auto_20201221_2107.py
kitchensink/migrations/0016_auto_20201221_2107.py
kitchensink/migrations/0017_auto_20210224_1933.py
kitchensink/migrations/0018_auto_20210224_2231.py
kitchensink/migrations/0019_auto_20210226_1823.py
kitchensink/migrations/0020_auto_20210316_1901.py
kitchensink/migrations/0021_auto_20210316_1936.py
kitchensink/migrations/0022_auto_20210325_2140.py
